Cel2Fa.py
Cel2Fa-1.0.1.dist-info/METADATA
Cel2Fa-1.0.1.dist-info/WHEEL
Cel2Fa-1.0.1.dist-info/entry_points.txt
Cel2Fa-1.0.1.dist-info/top_level.txt
Cel2Fa-1.0.1.dist-info/RECORD
