Metadata-Version: 2.1
Name: Cel2Fa
Version: 1.0.1
Summary: Read Celsius csv file and change to Fahrenheit
Home-page: https://github.com/HTuniv/CelsiusToFahrenheit
Author: Hyuga Taki
Author-email: 
License: UNKNOWN
Project-URL: Bug Tracker, https://github.com/HTuniv/CelsiusToFahrenheit
Platform: UNKNOWN
Classifier: Programming Language :: Python :: 3
Classifier: License :: OSI Approved :: MIT License
Classifier: Operating System :: OS Independent
Requires-Python: >=3.7
